{"stat.drop.excompressum.compressed_hammer_stone":1,"stat.leaveGame":5,"stat.pickup.extrautils2.redorchid":1,"stat.craftItem.excompressum.compressed_hammer_stone":1,"stat.mineBlock.extrautils2.compressedcobblestone":65,"stat.drop.exnihilocreatio.hammer_stone":4,"stat.pickup.minecraft.glowstone_dust":1,"stat.pickup.minecraft.blaze_powder":1,"stat.useItem.minecraft.water_bucket":27,"stat.pickup.exnihilocreatio.block_dust":99,"stat.pickup.minecraft.sand":506,"stat.craftItem.minecraft.stone_axe":1,"stat.pickup.minecraft.bucket":1,"stat.pickup.exnihilocreatio.item_pebble":924,"stat.mineBlock.exnihilocreatio.block_infested_leaves":65,"stat.pickup.integrateddynamics.menril_sapling":14,"stat.mineBlock.minecraft.sand":112,"stat.pickup.exnihilocreatio.item_ore_copper":11,"stat.craftItem.excompressum.bait":7,"stat.useItem.exnihilocreatio.item_material":8,"stat.useItem.minecraft.fence_gate":1,"stat.craftItem.stonechest.chest_cobblestone":1,"stat.pickup.projectred-core.resource_item":2,"stat.furnaceInteraction":16,"stat.useItem.minecraft.pumpkin_seeds":1,"stat.useItem.exnihilocreatio.item_cooked_silkworm":6,"stat.pickup.extrautils2.compressedsand":1,"stat.useItem.exnihilocreatio.item_seed_potato":2,"stat.pickup.exnihilocreatio.item_ore_iron":31,"stat.useItem.tconstruct.stone_torch":73,"stat.useItem.minecraft.fence":8,"stat.pickup.exnihilocreatio.item_ore_osmium":2,"stat.useItem.minecraft.stone_stairs":3,"stat.craftItem.minecraft.fence_gate":2,"stat.useItem.minecraft.wheat_seeds":2,"stat.pickup.exnihilocreatio.item_seed_carrot":4,"stat.pickup.minecraft.pumpkin_seeds":7,"stat.pickup.exnihilocreatio.item_ore_nickel":14,"stat.pickup.minecraft.emerald":1,"stat.useItem.minecraft.dye":12,"stat.pickup.minecraft.egg":3,"stat.pickup.actuallyadditions.item_dust":11,"stat.playOneMinute":353852,"stat.pickup.tconstruct.stone_torch":42,"stat.mineBlock.minecraft.tallgrass":109,"stat.chestOpened":130,"stat.pickup.thaumcraft.crystal_vitium":1,"stat.craftItem.minecraft.wheat_seeds":1,"stat.pickup.extrautils2.compressedcobblestone":1,"stat.craftItem.cyclicmagic.magnet_block":1,"stat.craftItem.minecraft.iron_nugget":9,"stat.fallOneCm":2110,"stat.drop.minecraft.dye":3,"stat.pickup.minecraft.carrot":5,"stat.pickup.minecraft.melon_seeds":11,"stat.crouchOneCm":725,"stat.craftItem.minecraft.iron_ingot":9,"stat.craftItem.minecraft.chest":8,"stat.pickup.minecraft.feather":1,"stat.pickup.exnihilocreatio.item_ore_gold":10,"stat.pickup.minecraft.dye":39,"stat.pickup.minecraft.wheat_seeds":15,"stat.mineBlock.minecraft.gravel":183,"stat.craftItem.roost.catcher":1,"stat.mineBlock.minecraft.dirt":72,"stat.pickup.minecraft.poisonous_potato":1,"stat.useItem.stoneblockutilities.crook_stone":321,"stat.pickup.exnihilocreatio.item_mesh":3,"stat.pickup.immersiveengineering.seed":3,"stat.mineBlock.extrautils2.compresseddirt":52,"stat.craftItem.minecraft.stone_stairs":4,"stat.useItem.minecraft.cobblestone":204,"stat.craftItem.extrautils2.compressedgravel":64,"stat.useItem.minecraft.gravel":172,"stat.pickup.excompressum.bait":3,"stat.pickup.minecraft.log":43,"stat.craftItem.exnihilocreatio.block_sieve":2,"stat.drop.minecraft.sapling":1,"stat.pickup.minecraft.chicken":1,"stat.pickup.minecraft.sapling":64,"stat.pickup.minecraft.apple":3,"stat.pickup.extrautils2.compresseddirt":1,"stat.craftItem.minecraft.bucket":1,"stat.craftItem.minecraft.planks":56,"stat.craftItem.stoneblockutilities.stoneworkbench":2,"stat.craftItem.tconstruct.stone_torch":104,"stat.mineBlock.minecraft.log":40,"stat.useItem.minecraft.stone_hoe":12,"stat.pickup.minecraft.red_flower":3,"stat.sneakTime":1397,"stat.pickup.exnihilocreatio.block_sieve":3,"stat.mineBlock.extrautils2.compressedgravel":64,"stat.pickup.minecraft.yellow_flower":6,"stat.craftItem.minecraft.cobblestone":121,"stat.craftItem.stonechest.part_cobblestone":6,"stat.mineBlock.minecraft.cobblestone":207,"stat.pickup.minecraft.flint":13,"stat.mineBlock.minecraft.yellow_flower":7,"stat.pickup.exnihilocreatio.item_ore_lead":2,"stat.craftItem.extrautils2.compressedcobblestone":64,"stat.swimOneCm":7842,"stat.useItem.minecraft.dirt":380,"stat.useItem.minecraft.stone_slab2":112,"stat.pickup.minecraft.cobblestone":3891,"stat.useItem.exnihilocreatio.hammer_stone":4398,"stat.flyOneCm":2237,"stat.pickup.appliedenergistics2.material":7,"stat.useItem.extrautils2.compressedgravel":63,"stat.craftItem.minecraft.wooden_slab":6,"stat.craftItem.extrautils2.compresseddirt":68,"stat.drop.minecraft.clay_ball":4,"stat.pickup.minecraft.redstone":3,"stat.timeSinceDeath":353852,"stat.pickup.exnihilocreatio.hammer_stone":3,"stat.pickup.actuallyadditions.item_rice_seed":16,"stat.pickup.hatchery.chickenmanure":11,"stat.mineBlock.excompressum.bait":3,"stat.craftItem.minecraft.stone_hoe":1,"stat.pickup.minecraft.string":100,"stat.craftItem.exnihilocreatio.hammer_stone":68,"stat.pickup.excompressum.compressed_hammer_stone":1,"stat.pickup.exnihilocreatio.item_ore_aluminium":6,"stat.craftItem.minecraft.stone_slab2":0,"stat.craftItem.tconstruct.stone_stick":184,"stat.craftItem.excompressum.heavy_sieve":1,"stat.sprintOneCm":69154,"stat.craftItem.minecraft.stick":36,"stat.pickup.exnihilocreatio.item_material":22,"stat.craftItem.minecraft.stone":108,"stat.useItem.excompressum.compressed_hammer_stone":199,"stat.drop.exnihilocreatio.block_dust":1,"stat.craftItem.minecraft.clay_ball":12,"stat.pickup.thaumcraft.crystal_aqua":1,"stat.drop":18,"stat.craftItem.excompressum.wooden_crucible":1,"stat.mineBlock.extrautils2.compressedsand":4,"stat.useItem.minecraft.melon_seeds":1,"stat.craftItem.minecraft.dye":5,"stat.craftItem.exnihilocreatio.item_cooked_silkworm":62,"stat.diveOneCm":2281,"stat.pickup.minecraft.wheat":8,"stat.pickup.minecraft.gravel":807,"stat.useItem.extrautils2.compressedcobblestone":63,"stat.useItem.minecraft.apple":5,"stat.pickup.exnihilocreatio.item_ore_tin":7,"stat.pickup.exnihilocreatio.item_seed_sugarcane":9,"stat.craftItem.exnihilocreatio.block_crucible":2,"stat.jump":420,"stat.useItem.minecraft.sand":107,"stat.pickup.minecraft.coal":12,"stat.useItem.exnihilocreatio.item_seed_carrot":2,"stat.pickup.minecraft.gunpowder":19,"stat.pickup.minecraft.dirt":1331,"stat.craftItem.stoneblockutilities.crook_stone":2,"stat.useItem.minecraft.sapling":6,"stat.pickup.actuallyadditions.item_flax_seed":12,"stat.craftItem.exnihilocreatio.item_ore_iron":9,"stat.pickup.actuallyadditions.item_coffee_seed":15,"stat.damageTaken":20,"stat.mineBlock.minecraft.torch":2,"stat.mineBlock.minecraft.red_flower":3,"stat.drop.minecraft.water_bucket":2,"stat.pickup.minecraft.reeds":3,"stat.pickup.exnihilocreatio.item_ore_silver":17,"stat.mineBlock.tconstruct.stone_torch":17,"stat.drop.tconstruct.stone_torch":2,"stat.pickup.exnihilocreatio.item_seed_potato":7,"stat.pickup.minecraft.potato":7,"stat.damageDealt":40,"stat.useItem.exnihilocreatio.item_seed_sugarcane":3,"stat.pickup.actuallyadditions.item_canola_seed":21,"stat.pickup.hatchery.hatcheryegg":1,"stat.walkOneCm":601710,"stat.craftItem.excompressum.compressed_block":6,"stat.animalsBred":1,"stat.useItem.minecraft.chest":7,"stat.craftItem.exnihilocreatio.item_material":8,"stat.useItem.minecraft.lava_bucket":1,"stat.killEntity.Chicken":1,"stat.mobKills":1,"stat.craftItem.minecraft.fence":12,"stat.pickup.minecraft.water_bucket":2,"stat.mineBlock.minecraft.leaves":256,"stat.pickup.minecraft.beetroot_seeds":12,"stat.pickup.minecraft.torch":2,"stat.craftItem.exnihilocreatio.item_mesh":7,"stat.mineBlock.minecraft.stone":3917,"stat.mineBlock.exnihilocreatio.block_sieve":3,"stat.useItem.extrautils2.compresseddirt":50,"stat.pickup.ftbquests.book":1}